poproblox/__init__.py
poproblox/core.py
poproblox-0.1.0.dist-info/licenses/LICENSE
poproblox-0.1.0.dist-info/METADATA
poproblox-0.1.0.dist-info/WHEEL
poproblox-0.1.0.dist-info/top_level.txt
poproblox-0.1.0.dist-info/RECORD
