Metadata-Version: 2.4
Name: poproblox
Version: 0.1.0
Summary: Start Roblox  +  Roblox Studio
Author: Cipherix
Classifier: Programming Language :: Python :: 3
Classifier: Operating System :: OS Independent
Requires-Python: >=3.6
License-File: LICENSE
Dynamic: author
Dynamic: classifier
Dynamic: license-file
Dynamic: requires-python
Dynamic: summary
